{
  "title": "10 Amazing Health Benefits of Green Tea",
  "author": "Dr. Sarah Johnson",
  "published_date": "2025-01-15",
  "content": "Green tea has been consumed for thousands of years and is one of the healthiest beverages on the planet. It's loaded with antioxidants and nutrients that have powerful effects on the body. This includes improved brain function, fat loss, a lower risk of cancer and many other incredible benefits. Here are 10 evidence-based health benefits of green tea that have been confirmed in human research studies.",
  "url": "https://example.com/health-benefits-green-tea",
  "summary": "Green tea offers numerous health benefits including improved brain function, fat loss, and cancer prevention due to its high antioxidant content."
}
